house_price_prediction/__init__.py
house_price_prediction/ingest_data.py
house_price_prediction/score.py
house_price_prediction/train.py
housing_library_5500-0.2.dist-info/LICENSE
housing_library_5500-0.2.dist-info/METADATA
housing_library_5500-0.2.dist-info/WHEEL
housing_library_5500-0.2.dist-info/entry_points.txt
housing_library_5500-0.2.dist-info/top_level.txt
housing_library_5500-0.2.dist-info/RECORD
