Metadata-Version: 2.1
Name: housing_library_5500
Version: 0.2
Summary: Sample code for coding practice
Author-email: Bidisha Mukherjee <bidisha.mukherje@tigeranalytics.com>
Project-URL: Homepage, https://github.com/BidiMukh28/mle-training.git
Keywords: housing,data training
Classifier: Programming Language :: Python :: 3
Classifier: License :: OSI Approved :: MIT License
Requires-Python: >=3.11
License-File: LICENSE
Requires-Dist: numpy
Requires-Dist: pandas
Requires-Dist: scikit-learn
